{
  "country": "southkorea",
  "generated_at": "2026-04-01T14:56:53Z",
  "categories": [
    "Diplomacy",
    "Military",
    "Energy",
    "Economy",
    "Local Events"
  ],
  "Diplomacy": [
    {
      "id": "79b393fa913434b0622f8c4d7e2c0edf",
      "title": "North Korea’s trade officials are running a pay-to-work racket",
      "source": "Daily NK",
      "url": "https://www.dailynk.com/english/north-koreas-trade-officials-are-running-a-pay-to-work-racket/",
      "published_date": "2026-04-01T14:34:00Z",
      "category": "Diplomacy"
    },
    {
      "id": "7f603308908f05c742551a3274ab9ce6",
      "title": "(2nd LD) S. Korea, U.S. discuss efforts to promote alliance through public diplomacy",
      "source": "Yonhap News Agency",
      "url": "https://en.yna.co.kr/view/AEN20260401009152315",
      "published_date": "2026-04-01T13:45:55Z",
      "category": "Diplomacy"
    },
    {
      "id": "527efc731447f3352976569aaa232fea",
      "title": "DP expels North Jeolla Gov. Kim Kwan-young over cash-handout allegations",
      "source": "Yonhap News Agency",
      "url": "https://en.yna.co.kr/view/AEN20260401012800320",
      "published_date": "2026-04-01T13:34:57Z",
      "category": "Diplomacy"
    },
    {
      "id": "982a443752cca36074967a7b9aab4907",
      "title": "North Korean traders make fake calls to cover Chinese phone use",
      "source": "Daily NK",
      "url": "https://www.dailynk.com/english/north-korean-traders-make-fake-calls-to-cover-chinese-phone-use/",
      "published_date": "2026-04-01T13:23:00Z",
      "category": "Diplomacy"
    },
    {
      "id": "923a01e4890697dc725eff295ab2661e",
      "title": "(LEAD) S. Korea, U.S. discuss efforts to promote alliance through public diplomacy",
      "source": "Yonhap News Agency",
      "url": "https://en.yna.co.kr/view/AEN20260401009151315",
      "published_date": "2026-04-01T11:06:31Z",
      "category": "Diplomacy"
    },
    {
      "id": "711be6ce29447e466177788fa3deb1aa",
      "title": "(LEAD) Lee calls for greater transparency on key supply chains amid Middle East tensions",
      "source": "Yonhap News Agency",
      "url": "https://en.yna.co.kr/view/AEN20260401012251315",
      "published_date": "2026-04-01T10:47:00Z",
      "category": "Diplomacy"
    },
    {
      "id": "f4c2edf6201d0955b75ba6a71e86d075",
      "title": "Russia issued over 36K visas to North Koreans in 2025, almost all for education",
      "source": "NK News",
      "url": "https://www.nknews.org/2026/04/russia-issued-over-36k-visas-to-north-koreans-in-2025-almost-all-for-education/",
      "published_date": "2026-04-01T09:39:28Z",
      "category": "Diplomacy"
    },
    {
      "id": "ea4965545332d990da920939b3e1e6ef",
      "title": "Ask a North Korean: Why North Koreans don’t trust state weather forecasts",
      "source": "NK News",
      "url": "https://www.nknews.org/2026/04/ask-a-north-korean-why-north-koreans-dont-trust-state-weather-forecasts/",
      "published_date": "2026-04-01T09:27:17Z",
      "category": "Diplomacy"
    },
    {
      "id": "80782d4539a535a4e46d38dd03bf580b",
      "title": "(3rd LD) Lee, Prabowo agree to elevate bilateral ties, expand defense industry cooperation",
      "source": "Yonhap News Agency",
      "url": "https://en.yna.co.kr/view/AEN20260401001453315",
      "published_date": "2026-04-01T09:26:21Z",
      "category": "Diplomacy"
    },
    {
      "id": "26e4ae783847fdd716509dbdbcb9e73c",
      "title": "Military, intel officers referred to prosecutors over North Korea drone flights",
      "source": "NK News",
      "url": "https://www.nknews.org/2026/04/military-intel-officers-referred-to-prosecutors-over-north-korea-drone-flights/",
      "published_date": "2026-04-01T08:42:09Z",
      "category": "Diplomacy"
    },
    {
      "id": "98dc35967362dcb7b38f36a5f0955b99",
      "title": "Lee calls for greater transparency on key supply chains amid Middle East tensions",
      "source": "Yonhap News Agency",
      "url": "https://en.yna.co.kr/view/AEN20260401012200315",
      "published_date": "2026-04-01T08:34:29Z",
      "category": "Diplomacy"
    },
    {
      "id": "63ee18f8ac37d5017270c36c70f2205b",
      "title": "Crackdowns can’t kill K-pop: BTS fandom thrives in North Korea",
      "source": "Daily NK",
      "url": "https://www.dailynk.com/english/crackdowns-cant-kill-k-pop-bts-fandom-thrives-in-north-korea/",
      "published_date": "2026-04-01T08:19:00Z",
      "category": "Diplomacy"
    },
    {
      "id": "b128340d6687a08541a1731a67de3d06",
      "title": "Crude oil supply from UAE en route to S. Korea as agreed: ministry",
      "source": "Yonhap News Agency",
      "url": "https://en.yna.co.kr/view/AEN20260401011000320",
      "published_date": "2026-04-01T07:59:15Z",
      "category": "Diplomacy"
    },
    {
      "id": "29e0c392b191dd91f7a0b3904c8951ef",
      "title": "Unification minister expresses condolences over death of former N. Korean IOC member",
      "source": "Yonhap News Agency",
      "url": "https://en.yna.co.kr/view/AEN20260401011500315",
      "published_date": "2026-04-01T07:54:20Z",
      "category": "Diplomacy"
    },
    {
      "id": "0f58fc551dd9400f9e59b9ef02815019",
      "title": "S. Korea, Indonesia agree to boost economic partnership, supply chain cooperation",
      "source": "Yonhap News Agency",
      "url": "https://en.yna.co.kr/view/AEN20260401010400320",
      "published_date": "2026-04-01T07:34:43Z",
      "category": "Diplomacy"
    },
    {
      "id": "ed8ea65eff5a9a9061b246b4750c6b84",
      "title": "GM Korea's March sales jump 24.2 pct on strong exports",
      "source": "Yonhap News Agency",
      "url": "https://en.yna.co.kr/view/AEN20260401010800320",
      "published_date": "2026-04-01T07:33:00Z",
      "category": "Diplomacy"
    },
    {
      "id": "cf8111f380d491949b50b99c52b40879",
      "title": "Renault Korea's March sales up 9 pct following Filante SUV launch",
      "source": "Yonhap News Agency",
      "url": "https://en.yna.co.kr/view/AEN20260401010700320",
      "published_date": "2026-04-01T07:31:50Z",
      "category": "Diplomacy"
    },
    {
      "id": "015d1dc5c6b1a1500dc42f8c3910e86f",
      "title": "Unification minister asks EU to mediate '2+1' dialogue with N. Korea",
      "source": "Yonhap News Agency",
      "url": "https://en.yna.co.kr/view/AEN20260401010600315",
      "published_date": "2026-04-01T07:29:08Z",
      "category": "Diplomacy"
    },
    {
      "id": "9d666777b9d0c906eee081dbaa459fe9",
      "title": "Hyundai Motor's March sales dip 2.3 pct as geopolitics affect global sales",
      "source": "Yonhap News Agency",
      "url": "https://en.yna.co.kr/view/AEN20260401010300320",
      "published_date": "2026-04-01T07:11:59Z",
      "category": "Diplomacy"
    },
    {
      "id": "209fdfb5e7088336045f9529afa8de82",
      "title": "S. Korea, U.S. discuss efforts to promote alliance through public diplomacy",
      "source": "Yonhap News Agency",
      "url": "https://en.yna.co.kr/view/AEN20260401009100315",
      "published_date": "2026-04-01T06:38:47Z",
      "category": "Diplomacy"
    }
  ],
  "Military": [
    {
      "id": "b0c608949ae4569c05d00bb74c223244",
      "title": "South Korea resumes remains recovery at major Korean War battle site in DMZ",
      "source": "NK News",
      "url": "https://www.nknews.org/2026/04/south-korea-resumes-remains-recovery-at-major-korean-war-battle-site-in-dmz/",
      "published_date": "2026-04-01T06:30:47Z",
      "category": "Military"
    },
    {
      "id": "06cdd92abaae82212e77114d75824d22",
      "title": "Army chiefs of S. Korea, U.S. discuss joint drills, military innovation",
      "source": "Yonhap News Agency",
      "url": "https://en.yna.co.kr/view/AEN20260401008700315",
      "published_date": "2026-04-01T06:21:36Z",
      "category": "Military"
    },
    {
      "id": "652c26f926fa8a7b8f03e652c53e9500",
      "title": "(Yonhap Interview) U.S. lawmaker optimistic about congressional backing for S. Korea's nuclear-powered sub, nuclear energy push",
      "source": "Yonhap News Agency",
      "url": "https://en.yna.co.kr/view/AEN20260401007200315",
      "published_date": "2026-04-01T03:13:22Z",
      "category": "Military"
    },
    {
      "id": "a37d713899f66ffe006fd447ace5ce12",
      "title": "Army chief discusses military ties with visiting Polish delegation",
      "source": "Yonhap News Agency",
      "url": "https://en.yna.co.kr/view/AEN20260401005400315",
      "published_date": "2026-04-01T02:18:50Z",
      "category": "Military"
    },
    {
      "id": "7f8bb8ca222d04ddf07fee0e1feaa7e8",
      "title": "Navy deploys MH-60R Seahawk helicopters for operation",
      "source": "Yonhap News Agency",
      "url": "https://en.yna.co.kr/view/AEN20260401003700315",
      "published_date": "2026-04-01T01:05:36Z",
      "category": "Military"
    },
    {
      "id": "cd0c762a8edd78e55f1dd69d5d56d5dd",
      "title": "(2nd LD) Hegseth: Upcoming days in Iran war will be 'decisive,' U.S. keeps all options open",
      "source": "Yonhap News Agency",
      "url": "https://en.yna.co.kr/view/AEN20260331012952315",
      "published_date": "2026-03-31T19:31:54Z",
      "category": "Military"
    },
    {
      "id": "59067ae020000dc8ffbdcb47bb04e747",
      "title": "(LEAD) Hegseth: Upcoming days in Iran war will be 'decisive,' U.S. keeps all options open",
      "source": "Yonhap News Agency",
      "url": "https://en.yna.co.kr/view/AEN20260331012951315",
      "published_date": "2026-03-31T14:55:05Z",
      "category": "Military"
    },
    {
      "id": "3f1c18184daabec5f0c3fb22198df2eb",
      "title": "Hegseth says upcoming days will be 'decisive' in Iran war, U.S. not foreclosing any option",
      "source": "Yonhap News Agency",
      "url": "https://en.yna.co.kr/view/AEN20260331012900315",
      "published_date": "2026-03-31T14:41:28Z",
      "category": "Military"
    },
    {
      "id": "960797fbf89d8b9120bf5263c7ba66e8",
      "title": "Defense ministry seeks to award military order to late lieutenant colonel killed in 1979 military coup",
      "source": "Yonhap News Agency",
      "url": "https://en.yna.co.kr/view/AEN20260331007800315",
      "published_date": "2026-03-31T07:22:34Z",
      "category": "Military"
    },
    {
      "id": "11bda1fe4596172dff374976f3f23863",
      "title": "Military protocol revised to raise rank of vice defense minister",
      "source": "Yonhap News Agency",
      "url": "https://en.yna.co.kr/view/AEN20260331007400315",
      "published_date": "2026-03-31T06:09:01Z",
      "category": "Military"
    },
    {
      "id": "95a86fb6e9d56592b2f07a137eab1625",
      "title": "LIG Nex1 rebranded as LIG D&A after shareholder approval",
      "source": "Yonhap News Agency",
      "url": "https://en.yna.co.kr/view/AEN20260331007200320",
      "published_date": "2026-03-31T05:36:32Z",
      "category": "Military"
    },
    {
      "id": "862dace027c4c94d9208752a26acc927",
      "title": "U.S. military squadron in Alaska joins live-fire drills in S. Korea",
      "source": "Yonhap News Agency",
      "url": "https://en.yna.co.kr/view/AEN20260331006600315",
      "published_date": "2026-03-31T04:16:34Z",
      "category": "Military"
    },
    {
      "id": "fd59b51dcdb67755a270ddfe08965564",
      "title": "NIS employee, 2 military officers referred to prosecution over drone flights to N. Korea",
      "source": "Yonhap News Agency",
      "url": "https://en.yna.co.kr/view/AEN20260331005800315",
      "published_date": "2026-03-31T02:17:36Z",
      "category": "Military"
    },
    {
      "id": "5f7e794a30517f39e5266760b58a1d4d",
      "title": "Late British Army Lt. Col. named Korean War hero of April",
      "source": "Yonhap News Agency",
      "url": "https://en.yna.co.kr/view/AEN20260331003800315",
      "published_date": "2026-03-31T01:31:40Z",
      "category": "Military"
    },
    {
      "id": "45f91b8291adebe8695a9f6110e1acbe",
      "title": "Hanwha Group wins U.S. Navy project as subcontractor for next-gen logistics ship",
      "source": "Yonhap News Agency",
      "url": "https://en.yna.co.kr/view/AEN20260331001600320",
      "published_date": "2026-03-30T23:57:01Z",
      "category": "Military"
    },
    {
      "id": "ad0ee28955f111242e44eea7134c6d3a",
      "title": "North Korean troops start reinforcing border again after monthslong pause: Seoul",
      "source": "NK News",
      "url": "https://www.nknews.org/2026/03/north-korean-troops-start-reinforcing-border-again-after-monthslong-pause-seoul/",
      "published_date": "2026-03-30T06:24:20Z",
      "category": "Military"
    },
    {
      "id": "58cccf487f27cdeac2360cdfe5751327",
      "title": "North Korea conducts missile engine test, claims higher thrust",
      "source": "NK News",
      "url": "https://www.nknews.org/2026/03/kim-jong-un-oversees-engine-test-state-media-claims-higher-thrust-capabilities/",
      "published_date": "2026-03-29T01:04:13Z",
      "category": "Military"
    },
    {
      "id": "0027b0114f9fc32344a13a7d5a2bd134",
      "title": "Trump says 'Cuba is next' as he highlights America's 'great' military",
      "source": "Yonhap News Agency",
      "url": "https://en.yna.co.kr/view/AEN20260328000400315",
      "published_date": "2026-03-27T23:39:26Z",
      "category": "Military"
    },
    {
      "id": "c13b527ed698d99cdcfe23126797eb75",
      "title": "Hanwha Systems wins 86.6 bln-won military satellite system maintenance deal",
      "source": "Yonhap News Agency",
      "url": "https://en.yna.co.kr/view/AEN20260327007900320",
      "published_date": "2026-03-27T07:33:51Z",
      "category": "Military"
    },
    {
      "id": "6f365c19c7d0d62b32bb6a2d83c6e59a",
      "title": "(LEAD) Lee vows to swiftly retake wartime command from U.S., speed up military reform including selective conscription",
      "source": "Yonhap News Agency",
      "url": "https://en.yna.co.kr/view/AEN20260327006751315",
      "published_date": "2026-03-27T07:27:05Z",
      "category": "Military"
    }
  ],
  "Energy": [
    {
      "id": "82d5bd0fb419cb053f56fc5553e9b8b2",
      "title": "Gov't raises energy disruption alert to second-highest level",
      "source": "Yonhap News Agency",
      "url": "https://en.yna.co.kr/view/AEN20260401011600320",
      "published_date": "2026-04-01T09:00:01Z",
      "category": "Energy"
    },
    {
      "id": "5955745bb4c366b6c65a0b2e5ec51fb5",
      "title": "Kia named best car manufacturer at Top Gear EV Awards 2026",
      "source": "Yonhap News Agency",
      "url": "https://en.yna.co.kr/view/AEN20260401008100320",
      "published_date": "2026-04-01T08:00:03Z",
      "category": "Energy"
    },
    {
      "id": "d8508a5583594a4d6542df50f3aa92dd",
      "title": "(2nd LD) Seoul stocks jump over 8 pct amid hopes for end to Middle East conflict",
      "source": "Yonhap News Agency",
      "url": "https://en.yna.co.kr/view/AEN20260401009352320",
      "published_date": "2026-04-01T07:45:35Z",
      "category": "Energy"
    },
    {
      "id": "dbd156ba2a2892ef449aaea5a667c053",
      "title": "(LEAD) Seoul stocks jump over 8 pct amid hopes for end to Middle East conflict",
      "source": "Yonhap News Agency",
      "url": "https://en.yna.co.kr/view/AEN20260401009351320",
      "published_date": "2026-04-01T07:03:01Z",
      "category": "Energy"
    },
    {
      "id": "4baf1c388f37ab3d098f1e3dd03ac649",
      "title": "Seoul stocks jump over 8 pct amid hopes for end to Middle East conflict",
      "source": "Yonhap News Agency",
      "url": "https://en.yna.co.kr/view/AEN20260401009300320",
      "published_date": "2026-04-01T06:37:05Z",
      "category": "Energy"
    },
    {
      "id": "7791b6e6f11e728068ee4cdb77042ea0",
      "title": "S. Korea, Indonesia sign MOU to expand AI, digital development exchanges",
      "source": "Yonhap News Agency",
      "url": "https://en.yna.co.kr/view/AEN20260401008200320",
      "published_date": "2026-04-01T06:11:25Z",
      "category": "Energy"
    },
    {
      "id": "52c23b1cba94ef962199f56e832678a6",
      "title": "(LEAD) Trade minister urges utmost efforts to secure oil, naphtha supplies amid Mideast crisis",
      "source": "Yonhap News Agency",
      "url": "https://en.yna.co.kr/view/AEN20260401002051320",
      "published_date": "2026-04-01T05:12:37Z",
      "category": "Energy"
    },
    {
      "id": "a094f03099e5602f53fb198a0765bad6",
      "title": "Media watchdog chief asks Google for efforts to support small app developers",
      "source": "Yonhap News Agency",
      "url": "https://en.yna.co.kr/view/AEN20260401007400320",
      "published_date": "2026-04-01T04:25:41Z",
      "category": "Energy"
    },
    {
      "id": "b8c0a78bb3c9024bde9e7d35badd595a",
      "title": "Airlines sharply raise fuel surcharges for April amid global oil price hike",
      "source": "Yonhap News Agency",
      "url": "https://en.yna.co.kr/view/AEN20260401006800320",
      "published_date": "2026-04-01T02:31:37Z",
      "category": "Energy"
    },
    {
      "id": "71773d00a021cca7b8babbf590fa191e",
      "title": "Trade minister urges utmost efforts to secure oil, naphtha supplies amid Mideast crisis",
      "source": "Yonhap News Agency",
      "url": "https://en.yna.co.kr/view/AEN20260401002000320",
      "published_date": "2026-04-01T00:13:13Z",
      "category": "Energy"
    },
    {
      "id": "b8db2299c9b8c82d6832f7f65c850108",
      "title": "(URGENT) S. Korea's chip exports hit record US$32.8 bln in March",
      "source": "Yonhap News Agency",
      "url": "https://en.yna.co.kr/view/AEN20260401002800320",
      "published_date": "2026-04-01T00:03:59Z",
      "category": "Energy"
    },
    {
      "id": "6be144c14da851d71f41d279586e8c2b",
      "title": "S. Korea coach pleased with defensive effort in friendly loss to Austria",
      "source": "Yonhap News Agency",
      "url": "https://en.yna.co.kr/view/AEN20260401000400315",
      "published_date": "2026-03-31T22:18:54Z",
      "category": "Energy"
    },
    {
      "id": "b646485ff210c9c26be6041ee1dd0af9",
      "title": "Over 70 S. Korean nationals evacuate from Iraq amid war in Middle East",
      "source": "Yonhap News Agency",
      "url": "https://en.yna.co.kr/view/AEN20260331012600315",
      "published_date": "2026-03-31T11:29:59Z",
      "category": "Energy"
    },
    {
      "id": "921d1ef2f94b8a5f7c6575998f321bfd",
      "title": "Korean Air to enter emergency management mode over soaring fuel costs",
      "source": "Yonhap News Agency",
      "url": "https://en.yna.co.kr/view/AEN20260331009000320",
      "published_date": "2026-03-31T06:54:39Z",
      "category": "Energy"
    },
    {
      "id": "02ea0170398e406e310c5d120015a65a",
      "title": "(LEAD) Gov't to introduce crude oil swap system with private companies for supply stabilization",
      "source": "Yonhap News Agency",
      "url": "https://en.yna.co.kr/view/AEN20260331006351320",
      "published_date": "2026-03-31T06:24:51Z",
      "category": "Energy"
    },
    {
      "id": "0e413ecf1c9e75dea6ab35ae9f09182c",
      "title": "Gov't to introduce crude oil swap system with private companies for supply stabilization",
      "source": "Yonhap News Agency",
      "url": "https://en.yna.co.kr/view/AEN20260331006300320",
      "published_date": "2026-03-31T02:40:19Z",
      "category": "Energy"
    },
    {
      "id": "0a3e7a174dce9c3934e1b32cb5ef9da3",
      "title": "(URGENT) Lee vows to take bold measures against concerns about energy supply, including emergency economic decree if needed",
      "source": "Yonhap News Agency",
      "url": "https://en.yna.co.kr/view/AEN20260331003600315",
      "published_date": "2026-03-31T01:15:04Z",
      "category": "Energy"
    },
    {
      "id": "6fe1a3da58627b109b41e9d497c0dc9b",
      "title": "Korean won hits fresh 17-yr low over heightened global oil supply concerns",
      "source": "Yonhap News Agency",
      "url": "https://en.yna.co.kr/view/AEN20260331002900320",
      "published_date": "2026-03-31T00:31:07Z",
      "category": "Energy"
    },
    {
      "id": "d2034627dbfe75ec5886b667862ac388",
      "title": "(4th LD) Trump threatens to 'obliterate' Iran's Kharg Island, power plants if deal is not reached 'shortly'",
      "source": "Yonhap News Agency",
      "url": "https://en.yna.co.kr/view/AEN20260330010154315",
      "published_date": "2026-03-30T20:57:30Z",
      "category": "Energy"
    },
    {
      "id": "95302b1e596e7eb36412251de86f6d2d",
      "title": "(3rd LD) Trump threatens to 'obliterate' Iran's Kharg Island, power plants if deal is not reached 'shortly'",
      "source": "Yonhap News Agency",
      "url": "https://en.yna.co.kr/view/AEN20260330010153315",
      "published_date": "2026-03-30T19:58:06Z",
      "category": "Energy"
    }
  ],
  "Economy": [
    {
      "id": "9de6cfe94a590b73b98639de79aaeaf3",
      "title": "(LEAD) Trump says Iran has asked for ceasefire, U.S. will consider it when Strait of Hormuz is open",
      "source": "Yonhap News Agency",
      "url": "https://en.yna.co.kr/view/AEN20260401012751315",
      "published_date": "2026-04-01T13:51:24Z",
      "category": "Economy"
    },
    {
      "id": "8e60359e4745d449a07a6bbd8e9914f9",
      "title": "Trump says Iran has asked for ceasefire, U.S. will consider it when Strait of Hormuz is open",
      "source": "Yonhap News Agency",
      "url": "https://en.yna.co.kr/view/AEN20260401012700315",
      "published_date": "2026-04-01T13:18:07Z",
      "category": "Economy"
    },
    {
      "id": "7024a38ed2ca4b47b454ae15865b3788",
      "title": "(LEAD) S. Korean currency surges on hope for Middle East de-escalation, WGBI inclusion",
      "source": "Yonhap News Agency",
      "url": "https://en.yna.co.kr/view/AEN20260401003451320",
      "published_date": "2026-04-01T06:50:58Z",
      "category": "Economy"
    },
    {
      "id": "b46cd03ff528c046bdfcc34182bae6fb",
      "title": "Gov't vows continued consultation with U.S. over USTR report on trade barriers",
      "source": "Yonhap News Agency",
      "url": "https://en.yna.co.kr/view/AEN20260401008800320",
      "published_date": "2026-04-01T06:50:29Z",
      "category": "Economy"
    },
    {
      "id": "2ec82f874dabb2019c7f9b7bce7d42ba",
      "title": "Major banks' household loans fall again in March amid tough curbs",
      "source": "Yonhap News Agency",
      "url": "https://en.yna.co.kr/view/AEN20260401008400320",
      "published_date": "2026-04-01T06:32:37Z",
      "category": "Economy"
    },
    {
      "id": "a2fa868d7c2368c464bc0fd72f880bd5",
      "title": "U.S. trade barrier report cites S. Korea's AI procurement, digital regulation, forced labor issues",
      "source": "Yonhap News Agency",
      "url": "https://en.yna.co.kr/view/AEN20260401008300315",
      "published_date": "2026-04-01T06:07:48Z",
      "category": "Economy"
    },
    {
      "id": "eea01d74edf590f1b68f0f9a968ef890",
      "title": "Science ministry launches agentic AI consultative body with LG, Kakao",
      "source": "Yonhap News Agency",
      "url": "https://en.yna.co.kr/view/AEN20260401004000320",
      "published_date": "2026-04-01T05:00:04Z",
      "category": "Economy"
    },
    {
      "id": "758399de79c0abfa52e3819d679ebcf6",
      "title": "Samsung Biologics acquires GSK's U.S. facility for US$280 mln",
      "source": "Yonhap News Agency",
      "url": "https://en.yna.co.kr/view/AEN20260401007000320",
      "published_date": "2026-04-01T02:46:58Z",
      "category": "Economy"
    },
    {
      "id": "8f07945b82bd8f302b692e5419b0d256",
      "title": "Seoul shares up sharply late Wed. morning amid hopes for end to Middle East war",
      "source": "Yonhap News Agency",
      "url": "https://en.yna.co.kr/view/AEN20260401006900320",
      "published_date": "2026-04-01T02:35:36Z",
      "category": "Economy"
    },
    {
      "id": "ea58826e5b3a1aa9416c5adee36be5f8",
      "title": "(2nd LD) S. Korea's monthly exports top US$80 bln mark for 1st time in March",
      "source": "Yonhap News Agency",
      "url": "https://en.yna.co.kr/view/AEN20260401002252320",
      "published_date": "2026-04-01T02:32:15Z",
      "category": "Economy"
    },
    {
      "id": "2035a55b14fe62eb5cc0b80621b59708",
      "title": "Gov't launches inter-ministerial task force to shore up exports",
      "source": "Yonhap News Agency",
      "url": "https://en.yna.co.kr/view/AEN20260401005500320",
      "published_date": "2026-04-01T02:12:38Z",
      "category": "Economy"
    },
    {
      "id": "0777a99cf6d4aaf2674b4f204f3f6689",
      "title": "Samsung Heavy wins 342 bln-won gas carrier order in Bermuda region",
      "source": "Yonhap News Agency",
      "url": "https://en.yna.co.kr/view/AEN20260401005100320",
      "published_date": "2026-04-01T01:57:12Z",
      "category": "Economy"
    },
    {
      "id": "d6d59ce1e676314f74f106471581de92",
      "title": "Lotte Biologics signs CDMO deal with U.S. firm for antibody drug substance",
      "source": "Yonhap News Agency",
      "url": "https://en.yna.co.kr/view/AEN20260401004500320",
      "published_date": "2026-04-01T01:35:38Z",
      "category": "Economy"
    },
    {
      "id": "013d907488b54738c886054fe4119785",
      "title": "(LEAD) Seoul launches new consultation body of top finance officials for macroeconomic response",
      "source": "Yonhap News Agency",
      "url": "https://en.yna.co.kr/view/AEN20260401003951320",
      "published_date": "2026-04-01T01:29:14Z",
      "category": "Economy"
    },
    {
      "id": "6f20afb0cacb58b367e35a453b395f86",
      "title": "Seoul launches new consultation body of top finance officials for macroeconomic response",
      "source": "Yonhap News Agency",
      "url": "https://en.yna.co.kr/view/AEN20260401003900320",
      "published_date": "2026-04-01T01:12:55Z",
      "category": "Economy"
    },
    {
      "id": "5964a0d0806b8b0b123f68c6456ed6cc",
      "title": "Celltrion to cancel 1.72 tln won in treasury shares to boost shareholder value",
      "source": "Yonhap News Agency",
      "url": "https://en.yna.co.kr/view/AEN20260401003800320",
      "published_date": "2026-04-01T01:06:29Z",
      "category": "Economy"
    },
    {
      "id": "4d8f83934ac5d6980e68621ddbb8985d",
      "title": "S. Korean currency surges on Trump's signaling of end to Middle East war",
      "source": "Yonhap News Agency",
      "url": "https://en.yna.co.kr/view/AEN20260401003400320",
      "published_date": "2026-04-01T00:54:48Z",
      "category": "Economy"
    },
    {
      "id": "03fc0cfa1f677891eee79d187be3fb8c",
      "title": "(LEAD) S. Korea's monthly exports top US$80 bln mark for 1st time in March",
      "source": "Yonhap News Agency",
      "url": "https://en.yna.co.kr/view/AEN20260401002251320",
      "published_date": "2026-04-01T00:39:25Z",
      "category": "Economy"
    },
    {
      "id": "db4bf3baf67bc7b87cae63d5ec36cd66",
      "title": "(LEAD) Seoul shares open sharply higher amid hopes for end to Middle East war",
      "source": "Yonhap News Agency",
      "url": "https://en.yna.co.kr/view/AEN20260401002951320",
      "published_date": "2026-04-01T00:25:54Z",
      "category": "Economy"
    },
    {
      "id": "09f41cd9a73c498ce0bad1e9beca9b63",
      "title": "(URGENT) Bourse operator issues buy-side sidecar for KOSPI market after sharp rise",
      "source": "Yonhap News Agency",
      "url": "https://en.yna.co.kr/view/AEN20260401003000320",
      "published_date": "2026-04-01T00:11:35Z",
      "category": "Economy"
    }
  ],
  "Local Events": [
    {
      "id": "a4a96087c04a73bd10a724b01ee6a543",
      "title": "(LEAD) Police seek arrest warrants for couple for abandoning mother's body in suitcase",
      "source": "Yonhap News Agency",
      "url": "https://en.yna.co.kr/view/AEN20260401004351315",
      "published_date": "2026-04-01T12:48:51Z",
      "category": "Local Events"
    },
    {
      "id": "924b78ff32391821928a36f5eaca79d3",
      "title": "Kia's March sales gain 2.7 pct on increased demand",
      "source": "Yonhap News Agency",
      "url": "https://en.yna.co.kr/view/AEN20260401012600320",
      "published_date": "2026-04-01T09:55:05Z",
      "category": "Local Events"
    },
    {
      "id": "26f7aa030d6883f502da4fdd7b85b9db",
      "title": "(LEAD) Gov't expands vehicle rotation system to 2-day scheme in public sector",
      "source": "Yonhap News Agency",
      "url": "https://en.yna.co.kr/view/AEN20260401012451320",
      "published_date": "2026-04-01T09:29:27Z",
      "category": "Local Events"
    },
    {
      "id": "bb4fe5f884d04b51eec8ad0d8ad1b6bc",
      "title": "Gov't expands vehicle rotation system to 2-day scheme in public sector",
      "source": "Yonhap News Agency",
      "url": "https://en.yna.co.kr/view/AEN20260401012400320",
      "published_date": "2026-04-01T09:04:13Z",
      "category": "Local Events"
    },
    {
      "id": "161a07009d30308823572e1c0ab07f35",
      "title": "Eagles pitcher Owen White out 6 weeks with hamstring injury",
      "source": "Yonhap News Agency",
      "url": "https://en.yna.co.kr/view/AEN20260401012300315",
      "published_date": "2026-04-01T08:31:46Z",
      "category": "Local Events"
    },
    {
      "id": "55d2fa4c78f9a1623656627d8018e93c",
      "title": "Yonhap News Summary",
      "source": "Yonhap News Agency",
      "url": "https://en.yna.co.kr/view/AEN20260401011700320",
      "published_date": "2026-04-01T07:56:57Z",
      "category": "Local Events"
    },
    {
      "id": "dc169698c80a81e85237e9e54abaa066",
      "title": "S. Korea's sports minister sends message of condolence over death of former N. Korean IOC member",
      "source": "Yonhap News Agency",
      "url": "https://en.yna.co.kr/view/AEN20260401004151315",
      "published_date": "2026-04-01T07:21:10Z",
      "category": "Local Events"
    },
    {
      "id": "69977fe353a952ea2178aa6c0282abff",
      "title": "Barricade around statue of girl symbolizing wartime sexual slavery victims lifted for 1st time in 6 yrs",
      "source": "Yonhap News Agency",
      "url": "https://en.yna.co.kr/view/AEN20260401010500315",
      "published_date": "2026-04-01T07:20:35Z",
      "category": "Local Events"
    },
    {
      "id": "f74064430f76489c1d53baa51251c701",
      "title": "Gov't to curb excessive classes at English kindergartens",
      "source": "Yonhap News Agency",
      "url": "https://en.yna.co.kr/view/AEN20260401010100315",
      "published_date": "2026-04-01T07:03:40Z",
      "category": "Local Events"
    },
    {
      "id": "e6a3c345812e17bf221456c1a0055e9f",
      "title": "KG Mobility's March sales rise 5.5 pct on domestic demand increase",
      "source": "Yonhap News Agency",
      "url": "https://en.yna.co.kr/view/AEN20260401009400320",
      "published_date": "2026-04-01T06:46:46Z",
      "category": "Local Events"
    },
    {
      "id": "3ad147fa0437f2fbf5a509b9d65456d8",
      "title": "(URGENT) KOSPI soars 8.44 pct to 5,478.7 amid hopes for end to Middle East conflict",
      "source": "Yonhap News Agency",
      "url": "https://en.yna.co.kr/view/AEN20260401009000320",
      "published_date": "2026-04-01T06:32:04Z",
      "category": "Local Events"
    },
    {
      "id": "211b7fc55dd5e86a5cb5e7e0a03fc032",
      "title": "S. Korea's WGBI inclusion could limit further rise in bond yields: analysts",
      "source": "Yonhap News Agency",
      "url": "https://en.yna.co.kr/view/AEN20260401007800320",
      "published_date": "2026-04-01T06:00:33Z",
      "category": "Local Events"
    },
    {
      "id": "dee2592c349ac94cefe76c72947d841e",
      "title": "N. Korea begins new school year on 1st day of April",
      "source": "Yonhap News Agency",
      "url": "https://en.yna.co.kr/view/AEN20260401008000315",
      "published_date": "2026-04-01T05:56:25Z",
      "category": "Local Events"
    },
    {
      "id": "c244a4e3e775679d15d8dc9f6529c15a",
      "title": "(3rd LD) Gov't to reopen all border walking trails for this year",
      "source": "Yonhap News Agency",
      "url": "https://en.yna.co.kr/view/AEN20260401001553315",
      "published_date": "2026-04-01T05:52:51Z",
      "category": "Local Events"
    },
    {
      "id": "feb9eb2f18fbf2ec3f706be72f7ea113",
      "title": "Today in Korean history",
      "source": "Yonhap News Agency",
      "url": "https://en.yna.co.kr/view/AEN20260401001000315",
      "published_date": "2026-04-01T05:00:06Z",
      "category": "Local Events"
    },
    {
      "id": "f8a860d5f8c05d2b6c2efe46027d0bd6",
      "title": "Yonhap News Summary",
      "source": "Yonhap News Agency",
      "url": "https://en.yna.co.kr/view/AEN20260401007500315",
      "published_date": "2026-04-01T04:30:20Z",
      "category": "Local Events"
    },
    {
      "id": "93409ba0129d8d296044e9368b4fdf6e",
      "title": "Apple improves iPhone's emergency location-sharing service for S. Korean users",
      "source": "Yonhap News Agency",
      "url": "https://en.yna.co.kr/view/AEN20260401006700320",
      "published_date": "2026-04-01T02:36:36Z",
      "category": "Local Events"
    },
    {
      "id": "f84aebddb159ff9c0eed21def30b4806",
      "title": "Ruling party, gov't confirm comprehensive survey of farmland ownership to curb property speculation",
      "source": "Yonhap News Agency",
      "url": "https://en.yna.co.kr/view/AEN20260401004800315",
      "published_date": "2026-04-01T01:54:02Z",
      "category": "Local Events"
    },
    {
      "id": "fa3b637d6693fd64126195cb56cedc82",
      "title": "S. Korea joins World Government Bond Index: minister",
      "source": "Yonhap News Agency",
      "url": "https://en.yna.co.kr/view/AEN20260401005000320",
      "published_date": "2026-04-01T01:52:36Z",
      "category": "Local Events"
    },
    {
      "id": "2ec3bdbdf6bda6aad5481efc03ad4b4a",
      "title": "Couple under probe for abandoning mother's body in suitcase",
      "source": "Yonhap News Agency",
      "url": "https://en.yna.co.kr/view/AEN20260401004300315",
      "published_date": "2026-04-01T01:35:41Z",
      "category": "Local Events"
    }
  ]
}